django_woohoo/__init__.py
django_woohoo/apps.py
django_woohoo/dataclasses.py
django_woohoo/helpers.py
django_woohoo/models.py
django_woohoo/signature.py
django_woohoo/utils.py
django_woohoo/migrations/0001_initial.py
django_woohoo/migrations/__init__.py
django_woohoo/migrations/__pycache__/0001_initial.cpython-312.pyc
django_woohoo/migrations/__pycache__/__init__.cpython-312.pyc
django_woohoo-0.1.0.dist-info/licenses/LICENSE
example_project/__init__.py
example_project/settings.py
example_project/urls.py
example_project/wsgi.py
django_woohoo-0.1.0.dist-info/METADATA
django_woohoo-0.1.0.dist-info/WHEEL
django_woohoo-0.1.0.dist-info/top_level.txt
django_woohoo-0.1.0.dist-info/RECORD
