Metadata-Version: 2.4
Name: django-woohoo
Version: 0.1.0
Summary: Django client for WooHoo gift card API integration
Home-page: https://github.com/sarthaklamba/django-woohoo
Author: Sarthak Lamba
Author-email: sarthaksnh5@gmail.com
Classifier: Framework :: Django
Classifier: Programming Language :: Python :: 3
Classifier: License :: OSI Approved :: MIT License
Classifier: Operating System :: OS Independent
Requires-Python: >=3.7
License-File: LICENSE
Requires-Dist: Django>=3.2
Requires-Dist: httpx
Requires-Dist: dataclasses-json
Dynamic: author
Dynamic: author-email
Dynamic: classifier
Dynamic: description
Dynamic: description-content-type
Dynamic: home-page
Dynamic: license-file
Dynamic: requires-dist
Dynamic: requires-python
Dynamic: summary
